ccbashhistory/__init__.py
ccbashhistory/cli.py
ccbashhistory/extractor.py
ccbashhistory-1.0.0.dist-info/METADATA
ccbashhistory-1.0.0.dist-info/WHEEL
ccbashhistory-1.0.0.dist-info/entry_points.txt
ccbashhistory-1.0.0.dist-info/top_level.txt
ccbashhistory-1.0.0.dist-info/RECORD
