Metadata-Version: 2.4
Name: ccbashhistory
Version: 1.0.0
Summary: Extract and analyze bash commands from Claude Code session history
Author: pdenya
License: MIT
Project-URL: Homepage, https://github.com/pdenya/ccbashhistory
Project-URL: Repository, https://github.com/pdenya/ccbashhistory
Project-URL: Issues, https://github.com/pdenya/ccbashhistory/issues
Keywords: claude,bash,history,command-line
Classifier: Development Status :: 4 - Beta
Classifier: Intended Audience :: Developers
Classifier: License :: OSI Approved :: MIT License
Classifier: Programming Language :: Python :: 3
Classifier: Programming Language :: Python :: 3.8
Classifier: Programming Language :: Python :: 3.9
Classifier: Programming Language :: Python :: 3.10
Classifier: Programming Language :: Python :: 3.11
Classifier: Programming Language :: Python :: 3.12
Classifier: Topic :: Software Development :: Libraries :: Python Modules
Requires-Python: >=3.8
